setup.py
easyssh/__init__.py
easyssh/ssh.py
easyssh/utils.py
easyssh.egg-info/PKG-INFO
easyssh.egg-info/SOURCES.txt
easyssh.egg-info/dependency_links.txt
easyssh.egg-info/requires.txt
easyssh.egg-info/top_level.txt