Metadata-Version: 1.0
Name: easyssh
Version: 4.6
Summary: to use python to take replace of ansible, saltstack
Home-page: https://github.com/intelyt/easyssh
Author: taoyin
Author-email: 1325869825@qq.com
License: Apache License 2.0
Platform: UNKNOWN
